mastercard_stp_api_sdk-1.0.0.dist-info/DESCRIPTION.rst
mastercard_stp_api_sdk-1.0.0.dist-info/METADATA
mastercard_stp_api_sdk-1.0.0.dist-info/RECORD
mastercard_stp_api_sdk-1.0.0.dist-info/WHEEL
mastercard_stp_api_sdk-1.0.0.dist-info/metadata.json
mastercard_stp_api_sdk-1.0.0.dist-info/top_level.txt
mastercardstpapisdk/__init__.py
mastercardstpapisdk/payment.py
mastercardstpapisdk/payments.py
mastercardstpapisdk/provider.py
mastercardstpapisdk/providers.py
mastercardstpapisdk/resourceconfig.py
mastercardstpapisdk/supplier.py
mastercardstpapisdk/suppliers.py
