Metadata-Version: 2.0
Name: mastercard-stp-api-sdk
Version: 1.0.0
Summary: MasterCard API Python SDK
Home-page: https://www.developer.mastercard.com
Author: MasterCard Worldwide
Author-email: APISupport@mastercard.com
License: BSD
Platform: UNKNOWN
Classifier: Intended Audience :: Developers
Classifier: Natural Language :: English
Classifier: Operating System :: OS Independent
Classifier: Programming Language :: Python :: 2.7
Classifier: Programming Language :: Python :: 3.5
Classifier: Programming Language :: Python :: 3.6
Classifier: Topic :: Software Development :: Libraries :: Python Modules
Requires-Dist: mastercard-api-core (<1.5.0,>=1.4.0)
